plenty_api/__init__.py
plenty_api/api.py
plenty_api/constants.py
plenty_api/keyring.py
plenty_api/utils.py
plenty_api-0.2.11.0.dist-info/LICENSE
plenty_api-0.2.11.0.dist-info/WHEEL
plenty_api-0.2.11.0.dist-info/METADATA
plenty_api-0.2.11.0.dist-info/RECORD
