Metadata-Version: 2.1
Name: plenty-api
Version: 0.2.11.0
Summary: Interface for the PlentyMarkets API.
Home-page: https://pypi.org/project/plenty_api
License: GPLv3
Keywords: plentymarkets,python,api,plenty,data
Author: Sebastian Fricke
Author-email: sebastian.fricke@posteo.net
Requires-Python: >=3.8,<4.0
Classifier: Development Status :: 1 - Planning
Classifier: License :: Other/Proprietary License
Classifier: Natural Language :: English
Classifier: Operating System :: OS Independent
Classifier: Programming Language :: Python
Classifier: Programming Language :: Python :: 3
Classifier: Programming Language :: Python :: 3.7
Classifier: Programming Language :: Python :: 3.8
Classifier: Programming Language :: Python :: 3.9
Requires-Dist: keyring (>=23.11.0,<24.0.0)
Requires-Dist: pandas (>=1.5.1,<2.0.0)
Requires-Dist: python-gnupg (>=0.5.0,<0.6.0)
Requires-Dist: requests (>=2.28.1,<3.0.0)
Requires-Dist: simplejson (>=3.17.6,<4.0.0)
Requires-Dist: tqdm (>=4.64.1,<5.0.0)
Project-URL: Repository, https://github.com/initBasti/python_plentymarkets_api
